einfunc/__about__.py
einfunc/__init__.py
einfunc/einfunc.py
einfunc-0.0.4.dist-info/METADATA
einfunc-0.0.4.dist-info/WHEEL
einfunc-0.0.4.dist-info/licenses/LICENSE.txt
einfunc-0.0.4.dist-info/RECORD
