Metadata-Version: 2.3
Name: einfunc
Version: 0.0.4
Summary: Einstein notation function which allows for simple, readible, and highly flexible tensor operations.
Project-URL: Documentation, https://github.com/Hprairie/einfunc#readme
Project-URL: Issues, https://github.com/Hprairie/einfunc/issues
Project-URL: Source, https://github.com/Hprairie/einfunc
Author-email: Hayden Prairie <haydenprairie@gmail.com>
License-Expression: MIT
License-File: LICENSE.txt
Classifier: Development Status :: 4 - Beta
Classifier: Programming Language :: Python
Classifier: Programming Language :: Python :: 3.8
Classifier: Programming Language :: Python :: 3.9
Classifier: Programming Language :: Python :: 3.10
Classifier: Programming Language :: Python :: 3.11
Classifier: Programming Language :: Python :: 3.12
Classifier: Programming Language :: Python :: Implementation :: CPython
Classifier: Programming Language :: Python :: Implementation :: PyPy
Requires-Python: >=3.8
